odoo/addons/pricelist_discount_decimal_accuracy/README.rst
odoo/addons/pricelist_discount_decimal_accuracy/__init__.py
odoo/addons/pricelist_discount_decimal_accuracy/__manifest__.py
odoo/addons/pricelist_discount_decimal_accuracy/models/__init__.py
odoo/addons/pricelist_discount_decimal_accuracy/models/product_pricelist_item.py
odoo/addons/pricelist_discount_decimal_accuracy/static/description/icon.png
odoo13_addon_pricelist_discount_decimal_accuracy-13.0.1.0.0.dist-info/METADATA
odoo13_addon_pricelist_discount_decimal_accuracy-13.0.1.0.0.dist-info/WHEEL
odoo13_addon_pricelist_discount_decimal_accuracy-13.0.1.0.0.dist-info/top_level.txt
odoo13_addon_pricelist_discount_decimal_accuracy-13.0.1.0.0.dist-info/RECORD
